pyirbrain/__init__.py
pyirbrain/deflib.py
pyirbrain/ikeyevent.py
pyirbrain/packet.py
pyirbrain/parse.py
pyirbrain/zeroDrone.py
pyirbrain-1.3.dist-info/METADATA
pyirbrain-1.3.dist-info/WHEEL
pyirbrain-1.3.dist-info/top_level.txt
pyirbrain-1.3.dist-info/RECORD
