Metadata-Version: 2.1
Name: pyirbrain
Version: 1.3
Summary: Library for IR-Brain Products
Home-page: http://www.ir-brain.com
Author: IR-Brain
Author-email: ceo@ir-brain.com
License: UNKNOWN
Platform: UNKNOWN
Requires-Dist: pyserial (>=3.4)
Requires-Dist: pynput (>=1.7.3)
